ZhengzebiaodashiJiaocheng30FenzhongRangNiJingtongZhengzebiaodashiYufa/README.md
ZhengzebiaodashiJiaocheng30FenzhongRangNiJingtongZhengzebiaodashiYufa/__init__.py
ZhengzebiaodashiJiaocheng30FenzhongRangNiJingtongZhengzebiaodashiYufa/__main__.py
ZhengzebiaodashiJiaocheng30FenzhongRangNiJingtongZhengzebiaodashiYufa/file.epub
ZhengzebiaodashiJiaocheng30FenzhongRangNiJingtongZhengzebiaodashiYufa/index.html
ZhengzebiaodashiJiaocheng30FenzhongRangNiJingtongZhengzebiaodashiYufa/css/__init__.py
ZhengzebiaodashiJiaocheng30FenzhongRangNiJingtongZhengzebiaodashiYufa/css/annotations.css
ZhengzebiaodashiJiaocheng30FenzhongRangNiJingtongZhengzebiaodashiYufa/css/main.css
ZhengzebiaodashiJiaocheng30FenzhongRangNiJingtongZhengzebiaodashiYufa/css/normalize.css
ZhengzebiaodashiJiaocheng30FenzhongRangNiJingtongZhengzebiaodashiYufa/css/popup.css
ZhengzebiaodashiJiaocheng30FenzhongRangNiJingtongZhengzebiaodashiYufa/font/__init__.py
ZhengzebiaodashiJiaocheng30FenzhongRangNiJingtongZhengzebiaodashiYufa/font/fontello.eot
ZhengzebiaodashiJiaocheng30FenzhongRangNiJingtongZhengzebiaodashiYufa/font/fontello.svg
ZhengzebiaodashiJiaocheng30FenzhongRangNiJingtongZhengzebiaodashiYufa/font/fontello.ttf
ZhengzebiaodashiJiaocheng30FenzhongRangNiJingtongZhengzebiaodashiYufa/font/fontello.woff
ZhengzebiaodashiJiaocheng30FenzhongRangNiJingtongZhengzebiaodashiYufa/img/__init__.py
ZhengzebiaodashiJiaocheng30FenzhongRangNiJingtongZhengzebiaodashiYufa/img/annotator-glyph-sprite.png
ZhengzebiaodashiJiaocheng30FenzhongRangNiJingtongZhengzebiaodashiYufa/img/annotator-icon-sprite.png
ZhengzebiaodashiJiaocheng30FenzhongRangNiJingtongZhengzebiaodashiYufa/img/apple-touch-icon.png
ZhengzebiaodashiJiaocheng30FenzhongRangNiJingtongZhengzebiaodashiYufa/img/cancelfullscreen.png
ZhengzebiaodashiJiaocheng30FenzhongRangNiJingtongZhengzebiaodashiYufa/img/close.png
ZhengzebiaodashiJiaocheng30FenzhongRangNiJingtongZhengzebiaodashiYufa/img/fullscreen.png
zhengzebiaodashi_jiaocheng_30_fenzhong_rang_ni_jingtong_zhengzebiaodashi_yufa-2024.3.2.0.dist-info/METADATA
zhengzebiaodashi_jiaocheng_30_fenzhong_rang_ni_jingtong_zhengzebiaodashi_yufa-2024.3.2.0.dist-info/WHEEL
zhengzebiaodashi_jiaocheng_30_fenzhong_rang_ni_jingtong_zhengzebiaodashi_yufa-2024.3.2.0.dist-info/entry_points.txt
zhengzebiaodashi_jiaocheng_30_fenzhong_rang_ni_jingtong_zhengzebiaodashi_yufa-2024.3.2.0.dist-info/top_level.txt
zhengzebiaodashi_jiaocheng_30_fenzhong_rang_ni_jingtong_zhengzebiaodashi_yufa-2024.3.2.0.dist-info/RECORD
